.gitignore
HISTORY.txt
MANIFEST.in
README.rst
README.txt
setup.cfg
setup.py
docs/INSTALL.txt
docs/LICENSE.GPL
docs/LICENSE.txt
docs/screen.png
wpd/__init__.py
wpd.countdown.egg-info/PKG-INFO
wpd.countdown.egg-info/SOURCES.txt
wpd.countdown.egg-info/dependency_links.txt
wpd.countdown.egg-info/entry_points.txt
wpd.countdown.egg-info/namespace_packages.txt
wpd.countdown.egg-info/not-zip-safe
wpd.countdown.egg-info/requires.txt
wpd.countdown.egg-info/top_level.txt
wpd/countdown/__init__.py
wpd/countdown/config.py
wpd/countdown/configure.zcml
wpd/countdown/setuphandlers.py
wpd/countdown/version.txt
wpd/countdown/browser/__init__.py
wpd/countdown/browser/configure.zcml
wpd/countdown/browser/views.py
wpd/countdown/browser/wpd-logo.gif
wpd/countdown/browser/wpdcountdown.pt
wpd/countdown/browser/wpdcountdown.py
wpd/countdown/locales/manual.pot
wpd/countdown/locales/rebuildAll.sh
wpd/countdown/locales/wpd.countdown.pot
wpd/countdown/locales/de/LC_MESSAGES/wpd.countdown.po
wpd/countdown/locales/pt_BR/LC_MESSAGES/wpd.countdown.po
wpd/countdown/profiles/default/controlpanel.xml
wpd/countdown/profiles/default/metadata.xml
wpd/countdown/profiles/default/portlets.xml
wpd/countdown/profiles/default/registry.xml
wpd/countdown/profiles/default/wpd.countdown.txt
wpd/countdown/tests/__init__.py
wpd/countdown/tests/base.py
wpd/countdown/tests/test_portlet.py