Metadata-Version: 1.0
Name: wpd.countdown
Version: 2.0
Summary: Countdown portlet for the World Plone Days
Home-page: https://github.com/collective/wpd.countdown
Author: Simples Consultoria
Author-email: products@simplesconsultoria.com.br
License: GPL
Keywords: plone worldploneday wpd countdown portlet
Platform: UNKNOWN
Classifier: Framework :: Plone
Classifier: Framework :: Zope2
Classifier: Framework :: Zope3
Classifier: Programming Language :: Python
Classifier: Topic :: Software Development :: Libraries :: Python Modules
